ragflow_mcp_server_continue/__init__.py
ragflow_mcp_server_continue/config.py
ragflow_mcp_server_continue/server.py
ragflow_mcp_server_continue-0.3.3.dist-info/METADATA
ragflow_mcp_server_continue-0.3.3.dist-info/WHEEL
ragflow_mcp_server_continue-0.3.3.dist-info/entry_points.txt
ragflow_mcp_server_continue-0.3.3.dist-info/RECORD
