Metadata-Version: 2.4
Name: ragflow-mcp-server-continue
Version: 0.3.3
Summary: RAGFlow MCP Server Continue
Requires-Python: >=3.10
Requires-Dist: click>=8.1.8
Requires-Dist: mcp>=1.12.2
Requires-Dist: python-dotenv>=1.1.0
Requires-Dist: ragflow-sdk>=0.19.1
